{
  "project_info": {
    "project_number": "533268395812",
    "project_id": "app-gamestore",
    "storage_bucket": "app-gamestore.appspot.com"
  },
  "client": [
    {
      "client_info": {
        "mobilesdk_app_id": "1:533268395812:android:d2ee0ab24f4867132ce5b1",
        "android_client_info": {
          "package_name": "com.example.learnfirebasekotlin"
        }
      },
      "oauth_client": [
        {
          "client_id": "533268395812-dne4a292rg17ri5ovud15i5keh21pvcs.apps.googleusercontent.com",
          "client_type": 3
        }
      ],
      "api_key": [
        {
          "current_key": "AIzaSyDgVhw4H90OzQPzHF6RNswf4e9v4y1-B50"
        }
      ],
      "services": {
        "appinvite_service": {
          "other_platform_oauth_client": [
            {
              "client_id": "533268395812-dne4a292rg17ri5ovud15i5keh21pvcs.apps.googleusercontent.com",
              "client_type": 3
            }
          ]
        }
      }
    }
  ],
  "configuration_version": "1"
}